Connors Python Menu/__init__.py
Connors Python Menu/api_client.py
ConnorsAPI/API.py
ConnorsAPI/__init__.py
ConnorsAPI/api_client.py
ConnorsAPI-0.2.2.dist-info/METADATA
ConnorsAPI-0.2.2.dist-info/WHEEL
ConnorsAPI-0.2.2.dist-info/top_level.txt
ConnorsAPI-0.2.2.dist-info/RECORD
