Metadata-Version: 2.1
Name: ConnorsAPI
Version: 0.2.2
Summary: A mod for API
Home-page: https://github.com/Concon6321/API-THINGY
Author: Connor Daniels
Author-email: youremail@example.com
